aiobatch/__init__.py
aiobatch/batcher.py
aiobatch/scheduler.py
aiobatch/task.py
aiobatch-0.0.1.dev5.dist-info/METADATA
aiobatch-0.0.1.dev5.dist-info/WHEEL
aiobatch-0.0.1.dev5.dist-info/licenses/LICENSE
aiobatch-0.0.1.dev5.dist-info/RECORD
